openmind_evaluate/__init__.py
openmind_evaluate/evaluate_adaptor.py
openmind_evaluate/patches/__init__.py
openmind_evaluate/patches/file_utils.py
openmind_evaluate/patches/loading.py
openmind_evaluate-0.7.0.dist-info/METADATA
openmind_evaluate-0.7.0.dist-info/WHEEL
openmind_evaluate-0.7.0.dist-info/licenses/LICENSE
openmind_evaluate-0.7.0.dist-info/RECORD
