Metadata-Version: 2.3
Name: openmind_evaluate
Version: 0.7.0
Summary: The openmind-evaluate is a product which allows you to use evaluate in openMind community.
Project-URL: Homepage, https://gitee.com/foundation-models/openmind-evaluate
Project-URL: Repository, https://gitee.com/foundation-models/openmind-evaluate
Author-email: The openmind-evaluate Team <contact@openmind.cn>
License:                      木兰宽松许可证, 第2版
License-File: LICENSE
Classifier: Development Status :: 1 - Planning
Classifier: Intended Audience :: Developers
Classifier: Intended Audience :: Education
Classifier: Intended Audience :: Science/Research
Classifier: License :: OSI Approved :: Apache Software License
Classifier: Operating System :: OS Independent
Classifier: Programming Language :: Python :: 3
Classifier: Programming Language :: Python :: 3.8
Classifier: Programming Language :: Python :: 3.9
Classifier: Programming Language :: Python :: 3.10
Classifier: Topic :: Scientific/Engineering :: Artificial Intelligence
Requires-Python: >=3.8
Requires-Dist: datasets==2.18.0
Requires-Dist: evaluate==0.4.1
Requires-Dist: huggingface-hub
Requires-Dist: openmind-hub
Requires-Dist: setuptools
Provides-Extra: lint
Requires-Dist: black; extra == 'lint'
Requires-Dist: ruff; extra == 'lint'
Provides-Extra: test
Requires-Dist: pytest; extra == 'test'
Requires-Dist: pytest-cov; extra == 'test'
